[
  {
    "id": 400,
    "category": 4,
    "name": "Macbook Pro 16\"",
    "nbid": 5,
    "owner": "eShop",
    "bidder": "admin",
    "price": 25700,
    "time": "2020-04-30T17:00+0700",
    "img": [
      "../../assets/products-pics/macbook.png",
      "../../assets/products-pics/macbook.png",
      "../../assets/products-pics/macbook.png"
    ]
  },
  {
    "id": 401,
    "category": 4,
    "name": "iPhone 11 64GB",
    "nbid": 22,
    "owner": "eShop",
    "bidder": "admin",
    "price": 26600,
    "time": "2020-05-02T17:00+0700",
    "img": [
      "../../assets/products-pics/macbook.png",
      "../../assets/products-pics/macbook.png",
      "../../assets/products-pics/macbook.png"
    ]
  },
  {
    "id": 402,
    "category": 4,
    "name": "A",
    "nbid": 22,
    "owner": "eShop",
    "bidder": "admin",
    "price": 26600,
    "time": "2020-05-02T17:00+0700",
    "img": [
      "../../assets/products-pics/macbook.png",
      "../../assets/products-pics/macbook.png",
      "../../assets/products-pics/macbook.png"
    ]
  },
  {
    "id": 403,
    "category": 4,
    "name": "B",
    "nbid": 2,
    "owner": "eShop",
    "bidder": "admin",
    "price": 1234,
    "time": "2020-05-12T17:00+0700",
    "img": [
      "../../assets/products-pics/macbook.png",
      "../../assets/products-pics/macbook.png",
      "../../assets/products-pics/macbook.png"
    ]
  }
]